docusign_monitor/__init__.py
docusign_monitor/apis/__init__.py
docusign_monitor/apis/data_set_api.py
docusign_monitor/client/__init__.py
docusign_monitor/client/api_client.py
docusign_monitor/client/api_exception.py
docusign_monitor/client/api_response.py
docusign_monitor/client/configuration.py
docusign_monitor/client/auth/__init__.py
docusign_monitor/client/auth/oauth.py
docusign_monitor/models/__init__.py
docusign_monitor/models/aggregate_result.py
docusign_monitor/models/aggregate_result_result.py
docusign_monitor/models/aggregation.py
docusign_monitor/models/cursored_result.py
docusign_monitor/models/data_set.py
docusign_monitor/models/filter.py
docusign_monitor/models/raw_request.py
docusign_monitor/models/web_query.py
test/__init__.py
test/test_oauth.py
test/unit_tests.py
docusign_monitor-1.2.0.dist-info/LICENSE
docusign_monitor-1.2.0.dist-info/METADATA
docusign_monitor-1.2.0.dist-info/WHEEL
docusign_monitor-1.2.0.dist-info/top_level.txt
docusign_monitor-1.2.0.dist-info/RECORD
