Metadata-Version: 2.1
Name: docusign-monitor
Version: 1.2.0
Summary: Monitor API
Home-page: 
Author-email: devcenter@docusign.com
Keywords: Swagger,Monitor API
License-File: LICENSE
